[
     {
          "id": 1,
          "name": "Abak"},
     {
          "id": 2,
          "name": "Abat"},
     {
          "id": 3,
          "name": "Afaha Ikot Ebak"},
     {
          "id": 4,
          "name": "Afaha Offiong"},
     {
          "id": 5,
          "name": "Eket"},
     {
          "id": 6,
          "name": "Enwang"},
     {
          "id": 7,
          "name": "Esuk Oron"},
     {
          "id": 8,
          "name": "Etinan"},
     {
          "id": 9,
          "name": "Eyofin"},
     {
          "id": 10,
          "name": "Ibiaku Ntok Okpo"},
     {
          "id": 11,
          "name": "Idu"},
     {
          "id": 12,
          "name": "Ikot Abasi"},
     {
          "id": 13,
          "name": "Ikot Akpa Nkuk"},
     {
          "id": 14,
          "name": "Ikot Edibon"},
     {
          "id": 15,
          "name": "Ikot Ekpene"},
     {
          "id": 16,
          "name": "Ikot Ibritam"},
     {
          "id": 17,
          "name": "Itu"},
     {
          "id": 18,
          "name": "Mkpat Enin"},
     {
          "id": 19,
          "name": "Nto Edino"},
     {
          "id": 20,
          "name": "Nung Udoe"},
     {
          "id": 21,
          "name": "Odoro Ikpe"},
     {
          "id": 22,
          "name": "Odot"},
     {
          "id": 23,
          "name": "Oko Ita"},
     {
          "id": 24,
          "name": "Okopedi"},
     {
          "id": 25,
          "name": "Okoroete"},
     {
          "id": 26,
          "name": "Oron"},
     {
          "id": 27,
          "name": "Upenekang"},
     {
          "id": 28,
          "name": "Uquo"},
     {
          "id": 29,
          "name": "Urua Inyang"},
     {
          "id": 30,
          "name": "Urue Offong"},
     {
          "id": 31,
          "name": "Utu Etim Ekpo"},
     {
          "id": 32,
          "name": "Uyo"}
]